storjcore/__init__.py
storjcore/audit.py
storjcore/auth.py
storjcore/encryptedio.py
storjcore/sanitize.py
storjcore/util.py
storjcore/version.py
storjcore-0.0.6.dist-info/DESCRIPTION.rst
storjcore-0.0.6.dist-info/METADATA
storjcore-0.0.6.dist-info/RECORD
storjcore-0.0.6.dist-info/WHEEL
storjcore-0.0.6.dist-info/metadata.json
storjcore-0.0.6.dist-info/top_level.txt
tests/__init__.py
tests/test_auth.py
tests/test_encryptedio.py
