Metadata-Version: 2.0
Name: storjcore
Version: 0.0.6
Summary: Client for storing and auditing data. http://storj.io
Home-page: http://storj.io
Author: Shawn Wilkinson
Author-email: shawn+storjcore@storj.io
License: MIT
Platform: UNKNOWN
Classifier: Development Status :: 2 - Pre-Alpha
Classifier: Intended Audience :: Developers
Classifier: License :: OSI Approved :: MIT License
Classifier: Operating System :: OS Independent
Classifier: Programming Language :: Python
Classifier: Programming Language :: Python :: 2
Classifier: Programming Language :: Python :: 2.7
Classifier: Programming Language :: Python :: 3
Classifier: Programming Language :: Python :: 3.3
Classifier: Programming Language :: Python :: 3.4
Classifier: Topic :: Software Development :: Libraries :: Python Modules
Requires-Dist: btctxstore (>=4.6.0)
Requires-Dist: partialhash (>=1.1.2)
Requires-Dist: pycrypto (>=2.6.1)
